circlemind/__init__.py
circlemind/_parser/__init__.py
circlemind/_parser/_base.py
circlemind/_parser/_pdf.py
circlemind/circlemind.py
circlemind-0.0.5.post2.dist-info/LICENSE.md
circlemind-0.0.5.post2.dist-info/METADATA
circlemind-0.0.5.post2.dist-info/WHEEL
circlemind-0.0.5.post2.dist-info/RECORD
