Metadata-Version: 2.1
Name: circlemind
Version: 0.0.5.post2
Summary: 
Author: Luca Pinchetti
Author-email: luca@circlemind.co
Requires-Python: >=3.9,<4.0
Classifier: Programming Language :: Python :: 3
Classifier: Programming Language :: Python :: 3.9
Classifier: Programming Language :: Python :: 3.10
Classifier: Programming Language :: Python :: 3.11
Classifier: Programming Language :: Python :: 3.12
Classifier: Programming Language :: Python :: 3.13
Classifier: Programming Language :: Python :: 3 :: Only
Classifier: Programming Language :: Python :: 3.8
Requires-Dist: circlemind-sdk (>=0.1.0-post0,<0.2.0)
Requires-Dist: pymupdf (>=1.24.13,<2.0.0)
Requires-Dist: pymupdf4llm (>=0.0.17,<0.0.18)
